{
  "myp-core": {
    "primary-colors": {
      "sea-green": {
        "value": "#9fe0b1",
        "type": "color"
      },
      "dim-green": {
        "value": "#f5fff1",
        "type": "color"
      },
      "light-green": {
        "value": "#55b570",
        "type": "color"
      },
      "dark-green": {
        "value": "#1a8a3a",
        "type": "color"
      },
      "deep-green": {
        "value": "#0b4422",
        "type": "color"
      }
    },
    "font-colors": {
      "black": {
        "value": "#292929",
        "type": "color"
      },
      "dark-grey": {
        "value": "#6f6f6f",
        "type": "color"
      },
      "light-grey": {
        "value": "#9d9a9a",
        "type": "color"
      },
      "white": {
        "value": "#ffffff",
        "type": "color"
      }
    },
    "stroke-for-white-obj": {
      "light-grey": {
        "value": "#afafaf",
        "type": "color"
      },
      "dark-grey": {
        "value": "#40464a",
        "type": "color"
      }
    },
    "property-bg": {
      "light-grey": {
        "value": "#dadada",
        "type": "color"
      },
      "dark-grey": {
        "value": "#40464a",
        "type": "color"
      },
      "charcoal": {
        "value": "#2f3436",
        "type": "color"
      }
    },
    "grey-bar": {
      "light-grey": {
        "value": "#6c7174",
        "type": "color"
      }
    },
    "toggle": {
      "Filled Grey": {
        "value": "#898d90",
        "type": "color"
      }
    },
    "fontFamilies": {
      "lato": {
        "value": "Lato",
        "type": "fontFamilies"
      }
    },
    "lineHeights": {
      "0": {
        "value": "80",
        "type": "lineHeights"
      },
      "1": {
        "value": "72",
        "type": "lineHeights"
      },
      "2": {
        "value": "56",
        "type": "lineHeights"
      },
      "3": {
        "value": "40",
        "type": "lineHeights"
      },
      "4": {
        "value": "32",
        "type": "lineHeights"
      },
      "5": {
        "value": "24",
        "type": "lineHeights"
      },
      "6": {
        "value": "20",
        "type": "lineHeights"
      },
      "7": {
        "value": "28",
        "type": "lineHeights"
      },
      "8": {
        "value": "26",
        "type": "lineHeights"
      },
      "9": {
        "value": "18",
        "type": "lineHeights"
      },
      "10": {
        "value": "14",
        "type": "lineHeights"
      }
    },
    "fontWeights": {
      "lato-0": {
        "value": "Regular",
        "type": "fontWeights"
      },
      "lato-1": {
        "value": "Bold",
        "type": "fontWeights"
      }
    },
    "fontSize": {
      "0": {
        "value": "10",
        "type": "fontSizes"
      },
      "1": {
        "value": "12",
        "type": "fontSizes"
      },
      "2": {
        "value": "14",
        "type": "fontSizes"
      },
      "3": {
        "value": "16",
        "type": "fontSizes"
      },
      "4": {
        "value": "18",
        "type": "fontSizes"
      },
      "5": {
        "value": "20",
        "type": "fontSizes"
      },
      "6": {
        "value": "24",
        "type": "fontSizes"
      },
      "7": {
        "value": "34",
        "type": "fontSizes"
      },
      "8": {
        "value": "48",
        "type": "fontSizes"
      },
      "9": {
        "value": "60",
        "type": "fontSizes"
      },
      "10": {
        "value": "72",
        "type": "fontSizes"
      }
    },
    "letterSpacing": {
      "0": {
        "value": "-4%",
        "type": "letterSpacing"
      },
      "1": {
        "value": "-2%",
        "type": "letterSpacing"
      },
      "2": {
        "value": "0%",
        "type": "letterSpacing"
      },
      "3": {
        "value": "2%",
        "type": "letterSpacing"
      }
    },
    "paragraphSpacing": {
      "0": {
        "value": "0",
        "type": "paragraphSpacing"
      }
    },
    "Display 01": {
      "Regular 72": {
        "value": {
          "fontFamily": "{fontFamilies.lato}",
          "fontWeight": "{fontWeights.lato-0}",
          "lineHeight": "{lineHeights.0}",
          "fontSize": "{fontSize.10}",
          "letterSpacing": "{letterSpacing.0}",
          "paragraphSpacing": "{paragraphSpacing.0}",
          "paragraphIndent": "{paragraphIndent.0}",
          "textCase": "{textCase.none}",
          "textDecoration": "{textDecoration.none}"
        },
        "type": "typography"
      },
      "Bold 72": {
        "value": {
          "fontFamily": "{fontFamilies.lato}",
          "fontWeight": "{fontWeights.lato-1}",
          "lineHeight": "{lineHeights.0}",
          "fontSize": "{fontSize.10}",
          "letterSpacing": "{letterSpacing.0}",
          "paragraphSpacing": "{paragraphSpacing.0}",
          "paragraphIndent": "{paragraphIndent.0}",
          "textCase": "{textCase.none}",
          "textDecoration": "{textDecoration.none}"
        },
        "type": "typography"
      }
    },
    "Display 02": {
      "Regular 60": {
        "value": {
          "fontFamily": "{fontFamilies.lato}",
          "fontWeight": "{fontWeights.lato-0}",
          "lineHeight": "{lineHeights.1}",
          "fontSize": "{fontSize.9}",
          "letterSpacing": "{letterSpacing.0}",
          "paragraphSpacing": "{paragraphSpacing.0}",
          "paragraphIndent": "{paragraphIndent.0}",
          "textCase": "{textCase.none}",
          "textDecoration": "{textDecoration.none}"
        },
        "type": "typography"
      },
      "Bold 60": {
        "value": {
          "fontFamily": "{fontFamilies.lato}",
          "fontWeight": "{fontWeights.lato-1}",
          "lineHeight": "{lineHeights.1}",
          "fontSize": "{fontSize.9}",
          "letterSpacing": "{letterSpacing.0}",
          "paragraphSpacing": "{paragraphSpacing.0}",
          "paragraphIndent": "{paragraphIndent.0}",
          "textCase": "{textCase.none}",
          "textDecoration": "{textDecoration.none}"
        },
        "type": "typography"
      }
    },
    "Heading 01": {
      "Regular 48": {
        "value": {
          "fontFamily": "{fontFamilies.lato}",
          "fontWeight": "{fontWeights.lato-0}",
          "lineHeight": "{lineHeights.2}",
          "fontSize": "{fontSize.8}",
          "letterSpacing": "{letterSpacing.0}",
          "paragraphSpacing": "{paragraphSpacing.0}",
          "paragraphIndent": "{paragraphIndent.0}",
          "textCase": "{textCase.none}",
          "textDecoration": "{textDecoration.none}"
        },
        "type": "typography"
      },
      "Bold 48": {
        "value": {
          "fontFamily": "{fontFamilies.lato}",
          "fontWeight": "{fontWeights.lato-1}",
          "lineHeight": "{lineHeights.2}",
          "fontSize": "{fontSize.8}",
          "letterSpacing": "{letterSpacing.0}",
          "paragraphSpacing": "{paragraphSpacing.0}",
          "paragraphIndent": "{paragraphIndent.0}",
          "textCase": "{textCase.none}",
          "textDecoration": "{textDecoration.none}"
        },
        "type": "typography"
      }
    },
    "Heading 02": {
      "Regular 34": {
        "value": {
          "fontFamily": "{fontFamilies.lato}",
          "fontWeight": "{fontWeights.lato-0}",
          "lineHeight": "{lineHeights.3}",
          "fontSize": "{fontSize.7}",
          "letterSpacing": "{letterSpacing.0}",
          "paragraphSpacing": "{paragraphSpacing.0}",
          "paragraphIndent": "{paragraphIndent.0}",
          "textCase": "{textCase.none}",
          "textDecoration": "{textDecoration.none}"
        },
        "type": "typography"
      },
      "Bold 34": {
        "value": {
          "fontFamily": "{fontFamilies.lato}",
          "fontWeight": "{fontWeights.lato-1}",
          "lineHeight": "{lineHeights.3}",
          "fontSize": "{fontSize.7}",
          "letterSpacing": "{letterSpacing.0}",
          "paragraphSpacing": "{paragraphSpacing.0}",
          "paragraphIndent": "{paragraphIndent.0}",
          "textCase": "{textCase.none}",
          "textDecoration": "{textDecoration.none}"
        },
        "type": "typography"
      }
    },
    "Heading 03": {
      "Regular 24": {
        "value": {
          "fontFamily": "{fontFamilies.lato}",
          "fontWeight": "{fontWeights.lato-0}",
          "lineHeight": "{lineHeights.4}",
          "fontSize": "{fontSize.6}",
          "letterSpacing": "{letterSpacing.1}",
          "paragraphSpacing": "{paragraphSpacing.0}",
          "paragraphIndent": "{paragraphIndent.0}",
          "textCase": "{textCase.none}",
          "textDecoration": "{textDecoration.none}"
        },
        "type": "typography"
      },
      "Bold 24": {
        "value": {
          "fontFamily": "{fontFamilies.lato}",
          "fontWeight": "{fontWeights.lato-1}",
          "lineHeight": "{lineHeights.4}",
          "fontSize": "{fontSize.6}",
          "letterSpacing": "{letterSpacing.1}",
          "paragraphSpacing": "{paragraphSpacing.0}",
          "paragraphIndent": "{paragraphIndent.0}",
          "textCase": "{textCase.none}",
          "textDecoration": "{textDecoration.none}"
        },
        "type": "typography"
      }
    },
    "Heading 04": {
      "Regular 20": {
        "value": {
          "fontFamily": "{fontFamilies.lato}",
          "fontWeight": "{fontWeights.lato-0}",
          "lineHeight": "{lineHeights.5}",
          "fontSize": "{fontSize.5}",
          "letterSpacing": "{letterSpacing.1}",
          "paragraphSpacing": "{paragraphSpacing.0}",
          "paragraphIndent": "{paragraphIndent.0}",
          "textCase": "{textCase.none}",
          "textDecoration": "{textDecoration.none}"
        },
        "type": "typography"
      },
      "Bold 20": {
        "value": {
          "fontFamily": "{fontFamilies.lato}",
          "fontWeight": "{fontWeights.lato-1}",
          "lineHeight": "{lineHeights.5}",
          "fontSize": "{fontSize.5}",
          "letterSpacing": "{letterSpacing.1}",
          "paragraphSpacing": "{paragraphSpacing.0}",
          "paragraphIndent": "{paragraphIndent.0}",
          "textCase": "{textCase.none}",
          "textDecoration": "{textDecoration.none}"
        },
        "type": "typography"
      }
    },
    "Heading 05": {
      "Regular 16": {
        "value": {
          "fontFamily": "{fontFamilies.lato}",
          "fontWeight": "{fontWeights.lato-0}",
          "lineHeight": "{lineHeights.6}",
          "fontSize": "{fontSize.3}",
          "letterSpacing": "{letterSpacing.1}",
          "paragraphSpacing": "{paragraphSpacing.0}",
          "paragraphIndent": "{paragraphIndent.0}",
          "textCase": "{textCase.none}",
          "textDecoration": "{textDecoration.none}"
        },
        "type": "typography"
      },
      "Bold 16": {
        "value": {
          "fontFamily": "{fontFamilies.lato}",
          "fontWeight": "{fontWeights.lato-1}",
          "lineHeight": "{lineHeights.6}",
          "fontSize": "{fontSize.3}",
          "letterSpacing": "{letterSpacing.1}",
          "paragraphSpacing": "{paragraphSpacing.0}",
          "paragraphIndent": "{paragraphIndent.0}",
          "textCase": "{textCase.none}",
          "textDecoration": "{textDecoration.none}"
        },
        "type": "typography"
      },
      "Regular  small 14": {
        "value": {
          "fontFamily": "{fontFamilies.lato}",
          "fontWeight": "{fontWeights.lato-0}",
          "lineHeight": "{lineHeights.6}",
          "fontSize": "{fontSize.2}",
          "letterSpacing": "{letterSpacing.1}",
          "paragraphSpacing": "{paragraphSpacing.0}",
          "paragraphIndent": "{paragraphIndent.0}",
          "textCase": "{textCase.none}",
          "textDecoration": "{textDecoration.none}"
        },
        "type": "typography"
      },
      "Bold Small 14": {
        "value": {
          "fontFamily": "{fontFamilies.lato}",
          "fontWeight": "{fontWeights.lato-1}",
          "lineHeight": "{lineHeights.6}",
          "fontSize": "{fontSize.2}",
          "letterSpacing": "{letterSpacing.1}",
          "paragraphSpacing": "{paragraphSpacing.0}",
          "paragraphIndent": "{paragraphIndent.0}",
          "textCase": "{textCase.none}",
          "textDecoration": "{textDecoration.none}"
        },
        "type": "typography"
      }
    },
    "Subheading": {
      "Regular 20": {
        "value": {
          "fontFamily": "{fontFamilies.lato}",
          "fontWeight": "{fontWeights.lato-0}",
          "lineHeight": "{lineHeights.7}",
          "fontSize": "{fontSize.5}",
          "letterSpacing": "{letterSpacing.2}",
          "paragraphSpacing": "{paragraphSpacing.0}",
          "paragraphIndent": "{paragraphIndent.0}",
          "textCase": "{textCase.none}",
          "textDecoration": "{textDecoration.none}"
        },
        "type": "typography"
      },
      "Bold 20": {
        "value": {
          "fontFamily": "{fontFamilies.lato}",
          "fontWeight": "{fontWeights.lato-1}",
          "lineHeight": "{lineHeights.7}",
          "fontSize": "{fontSize.5}",
          "letterSpacing": "{letterSpacing.2}",
          "paragraphSpacing": "{paragraphSpacing.0}",
          "paragraphIndent": "{paragraphIndent.0}",
          "textCase": "{textCase.none}",
          "textDecoration": "{textDecoration.none}"
        },
        "type": "typography"
      }
    },
    "Para 01": {
      "Regular 18": {
        "value": {
          "fontFamily": "{fontFamilies.lato}",
          "fontWeight": "{fontWeights.lato-0}",
          "lineHeight": "{lineHeights.8}",
          "fontSize": "{fontSize.4}",
          "letterSpacing": "{letterSpacing.2}",
          "paragraphSpacing": "{paragraphSpacing.0}",
          "paragraphIndent": "{paragraphIndent.0}",
          "textCase": "{textCase.none}",
          "textDecoration": "{textDecoration.none}"
        },
        "type": "typography"
      },
      "Bold 18": {
        "value": {
          "fontFamily": "{fontFamilies.lato}",
          "fontWeight": "{fontWeights.lato-1}",
          "lineHeight": "{lineHeights.8}",
          "fontSize": "{fontSize.4}",
          "letterSpacing": "{letterSpacing.2}",
          "paragraphSpacing": "{paragraphSpacing.0}",
          "paragraphIndent": "{paragraphIndent.0}",
          "textCase": "{textCase.none}",
          "textDecoration": "{textDecoration.none}"
        },
        "type": "typography"
      }
    },
    "Para 02": {
      "Regular 16": {
        "value": {
          "fontFamily": "{fontFamilies.lato}",
          "fontWeight": "{fontWeights.lato-0}",
          "lineHeight": "{lineHeights.5}",
          "fontSize": "{fontSize.3}",
          "letterSpacing": "{letterSpacing.2}",
          "paragraphSpacing": "{paragraphSpacing.0}",
          "paragraphIndent": "{paragraphIndent.0}",
          "textCase": "{textCase.none}",
          "textDecoration": "{textDecoration.none}"
        },
        "type": "typography"
      },
      "Bold 16": {
        "value": {
          "fontFamily": "{fontFamilies.lato}",
          "fontWeight": "{fontWeights.lato-1}",
          "lineHeight": "{lineHeights.5}",
          "fontSize": "{fontSize.3}",
          "letterSpacing": "{letterSpacing.2}",
          "paragraphSpacing": "{paragraphSpacing.0}",
          "paragraphIndent": "{paragraphIndent.0}",
          "textCase": "{textCase.none}",
          "textDecoration": "{textDecoration.none}"
        },
        "type": "typography"
      }
    },
    "Para 03": {
      "Regular 14": {
        "value": {
          "fontFamily": "{fontFamilies.lato}",
          "fontWeight": "{fontWeights.lato-0}",
          "lineHeight": "{lineHeights.6}",
          "fontSize": "{fontSize.2}",
          "letterSpacing": "{letterSpacing.2}",
          "paragraphSpacing": "{paragraphSpacing.0}",
          "paragraphIndent": "{paragraphIndent.0}",
          "textCase": "{textCase.none}",
          "textDecoration": "{textDecoration.none}"
        },
        "type": "typography"
      },
      "Bold 14": {
        "value": {
          "fontFamily": "{fontFamilies.lato}",
          "fontWeight": "{fontWeights.lato-1}",
          "lineHeight": "{lineHeights.6}",
          "fontSize": "{fontSize.2}",
          "letterSpacing": "{letterSpacing.2}",
          "paragraphSpacing": "{paragraphSpacing.0}",
          "paragraphIndent": "{paragraphIndent.0}",
          "textCase": "{textCase.none}",
          "textDecoration": "{textDecoration.none}"
        },
        "type": "typography"
      },
      "regular-14-underline": {
        "value": {
          "fontFamily": "{fontFamilies.lato}",
          "fontWeight": "{fontWeights.lato-0}",
          "lineHeight": "{lineHeights.6}",
          "fontSize": "{fontSize.2}",
          "letterSpacing": "{letterSpacing.2}",
          "paragraphSpacing": "{paragraphSpacing.0}",
          "paragraphIndent": "{paragraphIndent.0}",
          "textCase": "{textCase.none}",
          "textDecoration": "{textDecoration.underline}"
        },
        "type": "typography"
      },
      "regular-14-underline-copy": {
        "value": {
          "fontFamily": "{fontFamilies.lato}",
          "fontWeight": "{fontWeights.lato-0}",
          "lineHeight": "{lineHeights.6}",
          "fontSize": "{fontSize.2}",
          "letterSpacing": "{letterSpacing.2}",
          "paragraphSpacing": "{paragraphSpacing.0}",
          "paragraphIndent": "{paragraphIndent.0}",
          "textCase": "{textCase.none}",
          "textDecoration": "{textDecoration.underline}"
        },
        "type": "typography"
      }
    },
    "Caption": {
      "Regular 12": {
        "value": {
          "fontFamily": "{fontFamilies.lato}",
          "fontWeight": "{fontWeights.lato-0}",
          "lineHeight": "{lineHeights.9}",
          "fontSize": "{fontSize.1}",
          "letterSpacing": "{letterSpacing.2}",
          "paragraphSpacing": "{paragraphSpacing.0}",
          "paragraphIndent": "{paragraphIndent.0}",
          "textCase": "{textCase.none}",
          "textDecoration": "{textDecoration.none}"
        },
        "type": "typography"
      },
      "Bold 12": {
        "value": {
          "fontFamily": "{fontFamilies.lato}",
          "fontWeight": "{fontWeights.lato-1}",
          "lineHeight": "{lineHeights.9}",
          "fontSize": "{fontSize.1}",
          "letterSpacing": "{letterSpacing.2}",
          "paragraphSpacing": "{paragraphSpacing.0}",
          "paragraphIndent": "{paragraphIndent.0}",
          "textCase": "{textCase.none}",
          "textDecoration": "{textDecoration.none}"
        },
        "type": "typography"
      }
    },
    "Footer": {
      "Regular 10": {
        "value": {
          "fontFamily": "{fontFamilies.lato}",
          "fontWeight": "{fontWeights.lato-0}",
          "lineHeight": "{lineHeights.10}",
          "fontSize": "{fontSize.0}",
          "letterSpacing": "{letterSpacing.3}",
          "paragraphSpacing": "{paragraphSpacing.0}",
          "paragraphIndent": "{paragraphIndent.0}",
          "textCase": "{textCase.none}",
          "textDecoration": "{textDecoration.none}"
        },
        "type": "typography"
      },
      "Bold 10": {
        "value": {
          "fontFamily": "{fontFamilies.lato}",
          "fontWeight": "{fontWeights.lato-1}",
          "lineHeight": "{lineHeights.10}",
          "fontSize": "{fontSize.0}",
          "letterSpacing": "{letterSpacing.3}",
          "paragraphSpacing": "{paragraphSpacing.0}",
          "paragraphIndent": "{paragraphIndent.0}",
          "textCase": "{textCase.none}",
          "textDecoration": "{textDecoration.none}"
        },
        "type": "typography"
      }
    },
    "textCase": {
      "none": {
        "value": "none",
        "type": "textCase"
      }
    },
    "textDecoration": {
      "none": {
        "value": "none",
        "type": "textDecoration"
      },
      "underline": {
        "value": "underline",
        "type": "textDecoration"
      }
    },
    "common": {
      "white": {
        "value": "#ffffff",
        "type": "color"
      },
      "light-grey": {
        "value": "#b7b7b7",
        "type": "color"
      },
      "black": {
        "value": "#292929",
        "type": "color"
      },
      "pureblack": {
        "value": "#0000000",
        "type": "color"
      }
    },
    "stroke": {
      "white-alpha": {
        "value": "rgba($common.white, 255, 255, 255, 0.1)",
        "type": "color"
      },
      "white": {
        "value": "$common.white",
        "type": "color"
      }
    },
    "circles": {
      "beige": {
        "value": "#e9c38a",
        "type": "color"
      },
      "whitestroke": {
        "value": "$common.white",
        "type": "color"
      },
      "lightblue": {
        "value": "#83bbef",
        "type": "color"
      },
      "lightpurple": {
        "value": "#b6a8d6",
        "type": "color"
      },
      "lightcoral": {
        "value": "#cc526c",
        "type": "color"
      },
      "mouve": {
        "value": "#c693f9",
        "type": "color"
      },
      "yellow": {
        "value": "#f6c17b",
        "type": "color"
      },
      "white": {
        "value": "$common.white",
        "type": "color"
      },
      "blackstroke": {
        "value": "$common.pureblack",
        "type": "color"
      },
      "peach": {
        "value": "#f78f88",
        "type": "color"
      },
      "lightpeach": {
        "value": "#f9c3c0",
        "type": "color"
      },
      "lightpink": {
        "value": "#f9c0f6",
        "type": "color"
      },
      "earthpeach": {
        "value": "#dfb4b1",
        "type": "color"
      },
      "neavyblue": {
        "value": "#176ad4",
        "type": "color"
      },
      "darkblue": {
        "value": "#192b59",
        "type": "color"
      },
      "magenta": {
        "value": "#ab0d88",
        "type": "color"
      },
      "earthgrey": {
        "value": "#646464",
        "type": "color"
      },
      "green": {
        "value": "#22712A",
        "type": "color"
      },
      "brown": {
        "value": "#894F25",
        "type": "color"
      },
      "floresent": {
        "value": "#D8F993",
        "type": "color"
      }
    },
    "tooltip": {
      "general-shadow": {
        "value": {
          "x": "0",
          "y": "4",
          "blur": "4",
          "spread": "0",
          "color": "rgba(0, 0, 0, 0.25)",
          "type": "dropShadow"
        },
        "type": "boxShadow"
      }
    },
    "squares": {
      "watermelon-red": {
        "value": "#C14644",
        "type": "color"
      },
      "celestial-blue": {
        "value": "#4E8FC9",
        "type": "color"
      },
      "indian-yellow": {
        "value": "#E09E52",
        "type": "color"
      },
      "may-green": {
        "value": "#418D4B",
        "type": "color"
      },
      "dark-lavender": {
        "value": "#64539A",
        "type": "color"
      },
      "verdigris": {
        "value": "#55C1AC",
        "type": "color"
      },
      "davy's-grey": {
        "value": "#5B5B5B",
        "type": "color"
      },
      "pale-brown": {
        "value": "#957654",
        "type": "color"
      }
    },
    "icon-border": {
      "value": {
        "width": "1.5",
        "color": "#6f6f6f",
        "style": "solid"
      },
      "type": "border"
    },
    "white-stroke-1px": {
      "value": {
        "color": "$common.white",
        "width": "1",
        "style": "solid"
      },
      "type": "border"
    },
    "grey-stroke-1px": {
      "value": {
        "color": "$stroke-for-white-obj.light-grey",
        "width": "1",
        "style": "solid"
      },
      "type": "border"
    },
    "base-radius": {
      "4px": {
        "value": "4",
        "type": "borderRadius"
      },
      "8px": {
        "value": "{base-radius.4px} +4",
        "type": "borderRadius"
      },
      "12px": {
        "value": "{base-radius.8px} +4",
        "type": "borderRadius"
      },
      "16px": {
        "value": "{base-radius.12px} +4",
        "type": "borderRadius"
      },
      "20px": {
        "value": "{base-radius.16px} +4",
        "type": "borderRadius"
      },
      "24px": {
        "value": "{base-radius.20px} +4",
        "type": "borderRadius"
      },
      "28px": {
        "value": "$base-radius.24px +4",
        "type": "borderRadius"
      },
      "32px": {
        "value": "$base-radius.28px +4",
        "type": "borderRadius"
      },
      "full-radius": {
        "value": "100",
        "type": "borderRadius"
      }
    },
    "sidebar": {
      "mainshadow": {
        "value": {
          "x": "0",
          "y": "8",
          "blur": "8",
          "spread": "0",
          "color": "rgba(#000000, 0, 0, 0, 0.25)",
          "type": "dropShadow"
        },
        "type": "boxShadow"
      }
    }
  },
  "$themes": [],
  "$metadata": {
    "tokenSetOrder": [
      "myp-core"
    ]
  }
}